fenter_picsou/__init__.py
fenter_picsou/picsou.py
fenter_picsou-0.1.0.dist-info/METADATA
fenter_picsou-0.1.0.dist-info/WHEEL
fenter_picsou-0.1.0.dist-info/RECORD
