Metadata-Version: 2.1
Name: fenter-picsou
Version: 0.1.0
Summary: 
Author: VincentGGB
Author-email: 60670462+VincentGGB@users.noreply.github.com
Requires-Python: >=3.11,<4.0
Classifier: Programming Language :: Python :: 3
Classifier: Programming Language :: Python :: 3.11
Classifier: Programming Language :: Python :: 3.12
Requires-Dist: pillow (>=10.2.0,<11.0.0)
